xu/__init__.py
xu-0.2.0.dist-info/LICENSE
xu-0.2.0.dist-info/METADATA
xu-0.2.0.dist-info/WHEEL
xu-0.2.0.dist-info/top_level.txt
xu-0.2.0.dist-info/RECORD
