Metadata-Version: 2.1
Name: xu
Version: 0.2.0
Summary: Collection of handy random generators.
Home-page: https://github.com/onerbs/xu
Author: AAAA
Author-email: dev@onerbs.com
License: MIT
Keywords: random generator tool
Platform: UNKNOWN
Classifier: Development Status :: 3 - Alpha
Classifier: Intended Audience :: Developers
Classifier: License :: OSI Approved :: MIT License
Classifier: Operating System :: OS Independent
Classifier: Programming Language :: Python :: 3.8
Classifier: Programming Language :: Python :: 3.9
Classifier: Topic :: Software Development :: Libraries :: Python Modules
